qibotn/__init__.py
qibotn/backends/__init__.py
qibotn/backends/cutensornet.py
qibotn/backends/quimb.py
qibotn/circuit_convertor.py
qibotn/circuit_to_mps.py
qibotn/eval.py
qibotn/eval_qu.py
qibotn/mps_contraction_helper.py
qibotn/mps_utils.py
qibotn-0.0.2.dist-info/LICENSE
qibotn-0.0.2.dist-info/METADATA
qibotn-0.0.2.dist-info/WHEEL
qibotn-0.0.2.dist-info/RECORD
