Metadata-Version: 2.3
Name: qibotn
Version: 0.0.2
Summary: A tensor-network translation module for Qibo
License: Apache-2.0
Author: The Qibo team
Requires-Python: >=3.9,<3.13
Classifier: License :: OSI Approved :: Apache Software License
Classifier: Programming Language :: Python :: 3
Classifier: Programming Language :: Python :: 3.9
Classifier: Programming Language :: Python :: 3.10
Classifier: Programming Language :: Python :: 3.11
Classifier: Programming Language :: Python :: 3.12
Classifier: Topic :: Scientific/Engineering :: Physics
Provides-Extra: cuda
Requires-Dist: cupy-cuda11x (>=11.6.0,<12.0.0) ; extra == "cuda"
Requires-Dist: cuquantum-python-cu11 (>=23.3.0,<24.0.0) ; extra == "cuda"
Requires-Dist: mpi4py (>=3.1.5,<4.0.0) ; extra == "cuda"
Requires-Dist: qibo (>=0.2.8,<0.3.0)
Requires-Dist: quimb[tensor] (>=1.6.0,<2.0.0)
Project-URL: Documentation, https://qibo.science/docs/qibotn/stable
Project-URL: Homepage, https://qibo.science/
Project-URL: Repository, https://github.com/qiboteam/qibotn/
